{
  "StartDate": "2017-02-09T00:00:00",
  "EndDate": "2017-02-10T00:00:00",
  "RecordCount": 30,
  "Data": [
    {
      "Audit_Ser_Num": "3CQ6471N55",
      "Audit_Part_Num": "BNL-MON-TFT-23-WS-NEW",
      "Audit_Prod_Desc": "BAM NUTTAL 23\" TFT WIDE SCREEN",
      "Audit_Prod_Desc_Alt": "MONCLO",
      "Audit_Source_Site_Num": "",
      "Audit_Dest_Site_Num": "LTX",
      "Audit_Part_Type": "R",
      "Audit_Rem": "Added PO",
      "Audit_User": "CSTU",
      "Audit_Last_Update": "2017-02-09T15:41:44",
      "Audit_Move_Date": "2017-02-09T00:00:00"
    },
    {
      "Audit_Ser_Num": "3CQ6471N5H",
      "Audit_Part_Num": "BNL-MON-TFT-23-WS-NEW",
      "Audit_Prod_Desc": "BAM NUTTAL 23\" TFT WIDE SCREEN",
      "Audit_Prod_Desc_Alt": "MONCLO",
      "Audit_Source_Site_Num": "",
      "Audit_Dest_Site_Num": "LTX",
      "Audit_Part_Type": "R",
      "Audit_Rem": "Added PO",
      "Audit_User": "CSTU",
      "Audit_Last_Update": "2017-02-09T15:42:24",
      "Audit_Move_Date": "2017-02-09T00:00:00"
    },
    {
      "Audit_Ser_Num": "3CQ6471N5S",
      "Audit_Part_Num": "BNL-MON-TFT-23-WS-NEW",
      "Audit_Prod_Desc": "BAM NUTTAL 23\" TFT WIDE SCREEN",
      "Audit_Prod_Desc_Alt": "MONCLO",
      "Audit_Source_Site_Num": "",
      "Audit_Dest_Site_Num": "LTX",
      "Audit_Part_Type": "R",
      "Audit_Rem": "Added PO",
      "Audit_User": "CSTU",
      "Audit_Last_Update": "2017-02-09T15:43:02",
      "Audit_Move_Date": "2017-02-09T00:00:00"
    },
    {
      "Audit_Ser_Num": "3CQ6471N5V",
      "Audit_Part_Num": "BNL-MON-TFT-23-WS-NEW",
      "Audit_Prod_Desc": "BAM NUTTAL 23\" TFT WIDE SCREEN",
      "Audit_Prod_Desc_Alt": "MONCLO",
      "Audit_Source_Site_Num": "",
      "Audit_Dest_Site_Num": "LTX",
      "Audit_Part_Type": "R",
      "Audit_Rem": "Added PO",
      "Audit_User": "CSTU",
      "Audit_Last_Update": "2017-02-09T15:44:35",
      "Audit_Move_Date": "2017-02-09T00:00:00"
    },
    {
      "Audit_Ser_Num": "3CQ6471N66",
      "Audit_Part_Num": "BNL-MON-TFT-23-WS-NEW",
      "Audit_Prod_Desc": "BAM NUTTAL 23\" TFT WIDE SCREEN",
      "Audit_Prod_Desc_Alt": "MONCLO",
      "Audit_Source_Site_Num": "",
      "Audit_Dest_Site_Num": "LTX",
      "Audit_Part_Type": "R",
      "Audit_Rem": "Added PO",
      "Audit_User": "CSTU",
      "Audit_Last_Update": "2017-02-09T15:45:18",
      "Audit_Move_Date": "2017-02-09T00:00:00"
    },
    {
      "Audit_Ser_Num": "3CQ6471N5R",
      "Audit_Part_Num": "BNL-MON-TFT-23-WS-NEW",
      "Audit_Prod_Desc": "BAM NUTTAL 23\" TFT WIDE SCREEN",
      "Audit_Prod_Desc_Alt": "MONCLO",
      "Audit_Source_Site_Num": "",
      "Audit_Dest_Site_Num": "LTX",
      "Audit_Part_Type": "R",
      "Audit_Rem": "Added PO",
      "Audit_User": "CSTU",
      "Audit_Last_Update": "2017-02-09T15:45:20",
      "Audit_Move_Date": "2017-02-09T00:00:00"
    },
    {
      "Audit_Ser_Num": "3CQ6471N60",
      "Audit_Part_Num": "BNL-MON-TFT-23-WS-NEW",
      "Audit_Prod_Desc": "BAM NUTTAL 23\" TFT WIDE SCREEN",
      "Audit_Prod_Desc_Alt": "MONCLO",
      "Audit_Source_Site_Num": "",
      "Audit_Dest_Site_Num": "LTX",
      "Audit_Part_Type": "R",
      "Audit_Rem": "Added PO",
      "Audit_User": "CSTU",
      "Audit_Last_Update": "2017-02-09T15:45:36",
      "Audit_Move_Date": "2017-02-09T00:00:00"
    },
    {
      "Audit_Ser_Num": "3CQ6471N5N",
      "Audit_Part_Num": "BNL-MON-TFT-23-WS-NEW",
      "Audit_Prod_Desc": "BAM NUTTAL 23\" TFT WIDE SCREEN",
      "Audit_Prod_Desc_Alt": "MONCLO",
      "Audit_Source_Site_Num": "",
      "Audit_Dest_Site_Num": "LTX",
      "Audit_Part_Type": "R",
      "Audit_Rem": "Added PO",
      "Audit_User": "CSTU",
      "Audit_Last_Update": "2017-02-09T15:45:40",
      "Audit_Move_Date": "2017-02-09T00:00:00"
    },
    {
      "Audit_Ser_Num": "3CQ6471N65",
      "Audit_Part_Num": "BNL-MON-TFT-23-WS-NEW",
      "Audit_Prod_Desc": "BAM NUTTAL 23\" TFT WIDE SCREEN",
      "Audit_Prod_Desc_Alt": "MONCLO",
      "Audit_Source_Site_Num": "",
      "Audit_Dest_Site_Num": "LTX",
      "Audit_Part_Type": "R",
      "Audit_Rem": "Added PO",
      "Audit_User": "CSTU",
      "Audit_Last_Update": "2017-02-09T15:46:06",
      "Audit_Move_Date": "2017-02-09T00:00:00"
    },
    {
      "Audit_Ser_Num": "3CQ6471N63",
      "Audit_Part_Num": "BNL-MON-TFT-23-WS-NEW",
      "Audit_Prod_Desc": "BAM NUTTAL 23\" TFT WIDE SCREEN",
      "Audit_Prod_Desc_Alt": "MONCLO",
      "Audit_Source_Site_Num": "",
      "Audit_Dest_Site_Num": "LTX",
      "Audit_Part_Type": "R",
      "Audit_Rem": "Added PO",
      "Audit_User": "CSTU",
      "Audit_Last_Update": "2017-02-09T15:46:24",
      "Audit_Move_Date": "2017-02-09T00:00:00"
    },
    {
      "Audit_Ser_Num": "3CQ6471N5G",
      "Audit_Part_Num": "BNL-MON-TFT-23-WS-NEW",
      "Audit_Prod_Desc": "BAM NUTTAL 23\" TFT WIDE SCREEN",
      "Audit_Prod_Desc_Alt": "MONCLO",
      "Audit_Source_Site_Num": "",
      "Audit_Dest_Site_Num": "LTX",
      "Audit_Part_Type": "R",
      "Audit_Rem": "Added PO",
      "Audit_User": "CSTU",
      "Audit_Last_Update": "2017-02-09T15:46:27",
      "Audit_Move_Date": "2017-02-09T00:00:00"
    },
    {
      "Audit_Ser_Num": "3CQ6471N61",
      "Audit_Part_Num": "BNL-MON-TFT-23-WS-NEW",
      "Audit_Prod_Desc": "BAM NUTTAL 23\" TFT WIDE SCREEN",
      "Audit_Prod_Desc_Alt": "MONCLO",
      "Audit_Source_Site_Num": "",
      "Audit_Dest_Site_Num": "LTX",
      "Audit_Part_Type": "R",
      "Audit_Rem": "Added PO",
      "Audit_User": "CSTU",
      "Audit_Last_Update": "2017-02-09T15:46:47",
      "Audit_Move_Date": "2017-02-09T00:00:00"
    },
    {
      "Audit_Ser_Num": "3CQ6471N5P",
      "Audit_Part_Num": "BNL-MON-TFT-23-WS-NEW",
      "Audit_Prod_Desc": "BAM NUTTAL 23\" TFT WIDE SCREEN",
      "Audit_Prod_Desc_Alt": "MONCLO",
      "Audit_Source_Site_Num": "",
      "Audit_Dest_Site_Num": "LTX",
      "Audit_Part_Type": "R",
      "Audit_Rem": "Added PO",
      "Audit_User": "CSTU",
      "Audit_Last_Update": "2017-02-09T15:46:58",
      "Audit_Move_Date": "2017-02-09T00:00:00"
    },
    {
      "Audit_Ser_Num": "3CQ6471N5F",
      "Audit_Part_Num": "BNL-MON-TFT-23-WS-NEW",
      "Audit_Prod_Desc": "BAM NUTTAL 23\" TFT WIDE SCREEN",
      "Audit_Prod_Desc_Alt": "MONCLO",
      "Audit_Source_Site_Num": "",
      "Audit_Dest_Site_Num": "LTX",
      "Audit_Part_Type": "R",
      "Audit_Rem": "Added PO",
      "Audit_User": "CSTU",
      "Audit_Last_Update": "2017-02-09T15:47:06",
      "Audit_Move_Date": "2017-02-09T00:00:00"
    },
    {
      "Audit_Ser_Num": "3CQ6471N5M",
      "Audit_Part_Num": "BNL-MON-TFT-23-WS-NEW",
      "Audit_Prod_Desc": "BAM NUTTAL 23\" TFT WIDE SCREEN",
      "Audit_Prod_Desc_Alt": "MONCLO",
      "Audit_Source_Site_Num": "",
      "Audit_Dest_Site_Num": "LTX",
      "Audit_Part_Type": "R",
      "Audit_Rem": "Added PO",
      "Audit_User": "CSTU",
      "Audit_Last_Update": "2017-02-09T15:47:27",
      "Audit_Move_Date": "2017-02-09T00:00:00"
    },
    {
      "Audit_Ser_Num": "3CQ6471N7J",
      "Audit_Part_Num": "BNL-MON-TFT-23-WS-NEW",
      "Audit_Prod_Desc": "BAM NUTTAL 23\" TFT WIDE SCREEN",
      "Audit_Prod_Desc_Alt": "MONCLO",
      "Audit_Source_Site_Num": "",
      "Audit_Dest_Site_Num": "LTX",
      "Audit_Part_Type": "R",
      "Audit_Rem": "Added PO",
      "Audit_User": "CSTU",
      "Audit_Last_Update": "2017-02-09T15:47:44",
      "Audit_Move_Date": "2017-02-09T00:00:00"
    },
    {
      "Audit_Ser_Num": "3CQ6471N7K",
      "Audit_Part_Num": "BNL-MON-TFT-23-WS-NEW",
      "Audit_Prod_Desc": "BAM NUTTAL 23\" TFT WIDE SCREEN",
      "Audit_Prod_Desc_Alt": "MONCLO",
      "Audit_Source_Site_Num": "",
      "Audit_Dest_Site_Num": "LTX",
      "Audit_Part_Type": "R",
      "Audit_Rem": "Added PO",
      "Audit_User": "CSTU",
      "Audit_Last_Update": "2017-02-09T15:47:45",
      "Audit_Move_Date": "2017-02-09T00:00:00"
    },
    {
      "Audit_Ser_Num": "3CQ6471N5Z",
      "Audit_Part_Num": "BNL-MON-TFT-23-WS-NEW",
      "Audit_Prod_Desc": "BAM NUTTAL 23\" TFT WIDE SCREEN",
      "Audit_Prod_Desc_Alt": "MONCLO",
      "Audit_Source_Site_Num": "",
      "Audit_Dest_Site_Num": "LTX",
      "Audit_Part_Type": "R",
      "Audit_Rem": "Added PO",
      "Audit_User": "CSTU",
      "Audit_Last_Update": "2017-02-09T15:48:05",
      "Audit_Move_Date": "2017-02-09T00:00:00"
    },
    {
      "Audit_Ser_Num": "3CQ6471N7C",
      "Audit_Part_Num": "BNL-MON-TFT-23-WS-NEW",
      "Audit_Prod_Desc": "BAM NUTTAL 23\" TFT WIDE SCREEN",
      "Audit_Prod_Desc_Alt": "MONCLO",
      "Audit_Source_Site_Num": "",
      "Audit_Dest_Site_Num": "LTX",
      "Audit_Part_Type": "R",
      "Audit_Rem": "Added PO",
      "Audit_User": "CSTU",
      "Audit_Last_Update": "2017-02-09T15:51:11",
      "Audit_Move_Date": "2017-02-09T00:00:00"
    },
    {
      "Audit_Ser_Num": "3CQ6471N7D",
      "Audit_Part_Num": "BNL-MON-TFT-23-WS-NEW",
      "Audit_Prod_Desc": "BAM NUTTAL 23\" TFT WIDE SCREEN",
      "Audit_Prod_Desc_Alt": "MONCLO",
      "Audit_Source_Site_Num": "",
      "Audit_Dest_Site_Num": "LTX",
      "Audit_Part_Type": "R",
      "Audit_Rem": "Added PO",
      "Audit_User": "CSTU",
      "Audit_Last_Update": "2017-02-09T15:51:35",
      "Audit_Move_Date": "2017-02-09T00:00:00"
    },
    {
      "Audit_Ser_Num": "3CQ6471N7H",
      "Audit_Part_Num": "BNL-MON-TFT-23-WS-NEW",
      "Audit_Prod_Desc": "BAM NUTTAL 23\" TFT WIDE SCREEN",
      "Audit_Prod_Desc_Alt": "MONCLO",
      "Audit_Source_Site_Num": "",
      "Audit_Dest_Site_Num": "LTX",
      "Audit_Part_Type": "R",
      "Audit_Rem": "Added PO",
      "Audit_User": "CSTU",
      "Audit_Last_Update": "2017-02-09T15:51:46",
      "Audit_Move_Date": "2017-02-09T00:00:00"
    },
    {
      "Audit_Ser_Num": "3CQ6471N5Q",
      "Audit_Part_Num": "BNL-MON-TFT-23-WS-NEW",
      "Audit_Prod_Desc": "BAM NUTTAL 23\" TFT WIDE SCREEN",
      "Audit_Prod_Desc_Alt": "MONCLO",
      "Audit_Source_Site_Num": "",
      "Audit_Dest_Site_Num": "LTX",
      "Audit_Part_Type": "R",
      "Audit_Rem": "Added PO",
      "Audit_User": "CSTU",
      "Audit_Last_Update": "2017-02-09T15:52:25",
      "Audit_Move_Date": "2017-02-09T00:00:00"
    },
    {
      "Audit_Ser_Num": "3CQ6471N5K",
      "Audit_Part_Num": "BNL-MON-TFT-23-WS-NEW",
      "Audit_Prod_Desc": "BAM NUTTAL 23\" TFT WIDE SCREEN",
      "Audit_Prod_Desc_Alt": "MONCLO",
      "Audit_Source_Site_Num": "",
      "Audit_Dest_Site_Num": "LTX",
      "Audit_Part_Type": "R",
      "Audit_Rem": "Added PO",
      "Audit_User": "CSTU",
      "Audit_Last_Update": "2017-02-09T15:52:41",
      "Audit_Move_Date": "2017-02-09T00:00:00"
    },
    {
      "Audit_Ser_Num": "3CQ6471N5L",
      "Audit_Part_Num": "BNL-MON-TFT-23-WS-NEW",
      "Audit_Prod_Desc": "BAM NUTTAL 23\" TFT WIDE SCREEN",
      "Audit_Prod_Desc_Alt": "MONCLO",
      "Audit_Source_Site_Num": "",
      "Audit_Dest_Site_Num": "LTX",
      "Audit_Part_Type": "R",
      "Audit_Rem": "Added PO",
      "Audit_User": "CSTU",
      "Audit_Last_Update": "2017-02-09T15:52:51",
      "Audit_Move_Date": "2017-02-09T00:00:00"
    },
    {
      "Audit_Ser_Num": "3CQ6471N7M",
      "Audit_Part_Num": "BNL-MON-TFT-23-WS-NEW",
      "Audit_Prod_Desc": "BAM NUTTAL 23\" TFT WIDE SCREEN",
      "Audit_Prod_Desc_Alt": "MONCLO",
      "Audit_Source_Site_Num": "",
      "Audit_Dest_Site_Num": "LTX",
      "Audit_Part_Type": "R",
      "Audit_Rem": "Added PO",
      "Audit_User": "CSTU",
      "Audit_Last_Update": "2017-02-09T15:54:08",
      "Audit_Move_Date": "2017-02-09T00:00:00"
    },
    {
      "Audit_Ser_Num": "3CQ6471N7B",
      "Audit_Part_Num": "BNL-MON-TFT-23-WS-NEW",
      "Audit_Prod_Desc": "BAM NUTTAL 23\" TFT WIDE SCREEN",
      "Audit_Prod_Desc_Alt": "MONCLO",
      "Audit_Source_Site_Num": "",
      "Audit_Dest_Site_Num": "LTX",
      "Audit_Part_Type": "R",
      "Audit_Rem": "Added PO",
      "Audit_User": "CSTU",
      "Audit_Last_Update": "2017-02-09T15:54:10",
      "Audit_Move_Date": "2017-02-09T00:00:00"
    },
    {
      "Audit_Ser_Num": "3CQ6471N7R",
      "Audit_Part_Num": "BNL-MON-TFT-23-WS-NEW",
      "Audit_Prod_Desc": "BAM NUTTAL 23\" TFT WIDE SCREEN",
      "Audit_Prod_Desc_Alt": "MONCLO",
      "Audit_Source_Site_Num": "",
      "Audit_Dest_Site_Num": "LTX",
      "Audit_Part_Type": "R",
      "Audit_Rem": "Added PO",
      "Audit_User": "CSTU",
      "Audit_Last_Update": "2017-02-09T15:54:22",
      "Audit_Move_Date": "2017-02-09T00:00:00"
    },
    {
      "Audit_Ser_Num": "3CQ6471N7F",
      "Audit_Part_Num": "BNL-MON-TFT-23-WS-NEW",
      "Audit_Prod_Desc": "BAM NUTTAL 23\" TFT WIDE SCREEN",
      "Audit_Prod_Desc_Alt": "MONCLO",
      "Audit_Source_Site_Num": "",
      "Audit_Dest_Site_Num": "LTX",
      "Audit_Part_Type": "R",
      "Audit_Rem": "Added PO",
      "Audit_User": "CSTU",
      "Audit_Last_Update": "2017-02-09T15:54:52",
      "Audit_Move_Date": "2017-02-09T00:00:00"
    },
    {
      "Audit_Ser_Num": "3CQ6471N7G",
      "Audit_Part_Num": "BNL-MON-TFT-23-WS-NEW",
      "Audit_Prod_Desc": "BAM NUTTAL 23\" TFT WIDE SCREEN",
      "Audit_Prod_Desc_Alt": "MONCLO",
      "Audit_Source_Site_Num": "",
      "Audit_Dest_Site_Num": "LTX",
      "Audit_Part_Type": "R",
      "Audit_Rem": "Added PO",
      "Audit_User": "CSTU",
      "Audit_Last_Update": "2017-02-09T15:54:55",
      "Audit_Move_Date": "2017-02-09T00:00:00"
    },
    {
      "Audit_Ser_Num": "3CQ6471N79",
      "Audit_Part_Num": "BNL-MON-TFT-23-WS-NEW",
      "Audit_Prod_Desc": "BAM NUTTAL 23\" TFT WIDE SCREEN",
      "Audit_Prod_Desc_Alt": "MONCLO",
      "Audit_Source_Site_Num": "",
      "Audit_Dest_Site_Num": "LTX",
      "Audit_Part_Type": "R",
      "Audit_Rem": "Added PO",
      "Audit_User": "CSTU",
      "Audit_Last_Update": "2017-02-09T15:55:19",
      "Audit_Move_Date": "2017-02-09T00:00:00"
    }
  ]
}